LICENSE
README.md
setup.cfg
setup.py
aioplisio/__init__.py
aioplisio/plisio_client.py
aioplisio.egg-info/PKG-INFO
aioplisio.egg-info/SOURCES.txt
aioplisio.egg-info/dependency_links.txt
aioplisio.egg-info/top_level.txt
api/__init__.py
api/get_asyncio_api.py
utils/__init__.py
utils/base.py
utils/enums.py
utils/models.py
utils/plisio_exceptions.py