Metadata-Version: 2.1
Name: aioplisio
Version: 1.0.0
Summary: Asynchronous wrapper for Plisio API
Home-page: https://github.com/Fsoky/aioplisio
Author: Fsoky
Author-email: cyberuest0x12@gmail.com
License: UNKNOWN
Keywords: api plisio crypto cryptopay plisio-api
Platform: UNKNOWN
License-File: LICENSE
